chainmaker/__init__.py
chainmaker/chain_client.py
chainmaker/chain_manager.py
chainmaker/client_node.py
chainmaker/client_user.py
chainmaker/conn_pool.py
chainmaker/exceptions.py
chainmaker/keys.py
chainmaker/node.py
chainmaker/payload.py
chainmaker/sdk_config.py
chainmaker/user.py
chainmaker/apis/__init__.py
chainmaker/apis/account_manager.py
chainmaker/apis/archive_manage.py
chainmaker/apis/base_client.py
chainmaker/apis/cert_manage.py
chainmaker/apis/chain_config.py
chainmaker/apis/chain_query.py
chainmaker/apis/chainmaker_server.py
chainmaker/apis/consensus.py
chainmaker/apis/contract_manage.py
chainmaker/apis/cross_transaction.py
chainmaker/apis/dpos_distribution.py
chainmaker/apis/dpos_erc20.py
chainmaker/apis/dpos_slashing.py
chainmaker/apis/dpos_stake.py
chainmaker/apis/multi_sign.py
chainmaker/apis/private_compute.py
chainmaker/apis/pubkey_manage.py
chainmaker/apis/relay_cross.py
chainmaker/apis/subscribe_manage.py
chainmaker/apis/transaction_manager.py
chainmaker/apis/txpool.py
chainmaker/archive_service/__init__.py
chainmaker/archive_service/archive_center_grpc_client.py
chainmaker/archive_service/archive_center_http_client.py
chainmaker/archive_service/archive_mysql_client.py
chainmaker/archive_service/archive_service.py
chainmaker/protos/__init__.py
chainmaker/protos/accesscontrol/member_pb2.py
chainmaker/protos/accesscontrol/member_pb2_grpc.py
chainmaker/protos/accesscontrol/policy_pb2.py
chainmaker/protos/accesscontrol/policy_pb2_grpc.py
chainmaker/protos/api/rpc_node_pb2.py
chainmaker/protos/api/rpc_node_pb2_grpc.py
chainmaker/protos/archivecenter/archivecenter_pb2.py
chainmaker/protos/archivecenter/archivecenter_pb2_grpc.py
chainmaker/protos/common/birdsnest_pb2.py
chainmaker/protos/common/birdsnest_pb2_grpc.py
chainmaker/protos/common/block_pb2.py
chainmaker/protos/common/block_pb2_grpc.py
chainmaker/protos/common/contract_pb2.py
chainmaker/protos/common/contract_pb2_grpc.py
chainmaker/protos/common/request_pb2.py
chainmaker-3.0.7.dist-info/LICENSE
chainmaker-3.0.7.dist-info/METADATA
chainmaker-3.0.7.dist-info/NOTICE
chainmaker-3.0.7.dist-info/WHEEL
chainmaker-3.0.7.dist-info/top_level.txt
chainmaker-3.0.7.dist-info/zip-safe
chainmaker-3.0.7.dist-info/RECORD
