Metadata-Version: 2.1
Name: chainmaker
Version: 3.0.7
Summary: ChainMaker Python SDK
Home-page: https://git.chainmaker.org.cn/chainmaker/chainmaker-sdk-python.git
Author: THL chainmaker developers
Author-email: operation@chainmaker.org
License: Apache License
Keywords: chainmaker,blockchain,chainmaker-sdk-python,chainmaker-sdk
Classifier: Development Status :: 3 - Alpha
Classifier: Topic :: Software Development :: User Interfaces
Classifier: Programming Language :: Python
Classifier: Programming Language :: Python :: 3.6
Classifier: Programming Language :: Python :: 3.7
Classifier: Programming Language :: Python :: 3.8
Classifier: Programming Language :: Python :: 3.9
Classifier: Programming Language :: Python :: 3.10
License-File: LICENSE
License-File: NOTICE
Requires-Dist: protobuf
Requires-Dist: grpcio
Requires-Dist: pyyaml
Requires-Dist: cryptography
Requires-Dist: pysha3
Requires-Dist: pymysql
Requires-Dist: eth-abi (>2.6)
Requires-Dist: asn1
Requires-Dist: pyasn1
Requires-Dist: pyasn1-modules
Requires-Dist: requests
